envchain_shellenv/__init__.py
envchain_shellenv/cli.py
envchain_shellenv/config.py
envchain_shellenv/core.py
envchain_shellenv/examples/keychain.ini
envchain_shellenv/examples/keychain.yaml
envchain_shellenv/types.py
envchain_shellenv-1.0.2.dist-info/entry_points.txt
envchain_shellenv-1.0.2.dist-info/LICENSE
envchain_shellenv-1.0.2.dist-info/WHEEL
envchain_shellenv-1.0.2.dist-info/METADATA
envchain_shellenv-1.0.2.dist-info/RECORD
